{"errors":[],"warnings":[],"namedChunkGroups":{"polyfill":{"chunks":[0,6],"assets":["webpack-runtime-041491fd28ee0c843732.js","webpack-runtime-041491fd28ee0c843732.js.map","polyfill-38cce18603b1d20cac17.js","polyfill-38cce18603b1d20cac17.js.map"],"children":{},"childAssets":{}},"app":{"chunks":[0,4,2],"assets":["webpack-runtime-041491fd28ee0c843732.js","webpack-runtime-041491fd28ee0c843732.js.map","framework-06f646d936b841f99ebd.js","framework-06f646d936b841f99ebd.js.map","app-a6ea04d8e800f46a7498.js","app-a6ea04d8e800f46a7498.js.map"],"children":{},"childAssets":{}},"component---src-pages-index-js":{"chunks":[7,1,3],"assets":["styles.3dbdc744c1849bed8160.css","styles-9411612e31e4f14527d1.js","styles-9411612e31e4f14527d1.js.map","2b7b2d2a-928237e1a16142be2485.js","2b7b2d2a-928237e1a16142be2485.js.map","component---src-pages-index-js-bb56f6fad2bb3c19095e.js","component---src-pages-index-js-bb56f6fad2bb3c19095e.js.map"],"children":{},"childAssets":{}},"pdfjsWorker":{"chunks":[5],"assets":["pdfjsWorker-c9e0e6fdaf80fd03f5c9.js","pdfjsWorker-c9e0e6fdaf80fd03f5c9.js.map"],"children":{},"childAssets":{}}},"assetsByChunkName":{"polyfill":["webpack-runtime-041491fd28ee0c843732.js","polyfill-38cce18603b1d20cac17.js"],"app":["webpack-runtime-041491fd28ee0c843732.js","framework-06f646d936b841f99ebd.js","app-a6ea04d8e800f46a7498.js"],"component---src-pages-index-js":["styles.3dbdc744c1849bed8160.css","styles-9411612e31e4f14527d1.js","2b7b2d2a-928237e1a16142be2485.js","component---src-pages-index-js-bb56f6fad2bb3c19095e.js"],"pdfjsWorker":["pdfjsWorker-c9e0e6fdaf80fd03f5c9.js"]}}